pywreck/__init__.py
pywreck/py.typed
pywreck/version.txt
pywreck-0.6.0.dist-info/licenses/LICENSE
pywreck-0.6.0.dist-info/METADATA
pywreck-0.6.0.dist-info/WHEEL
pywreck-0.6.0.dist-info/top_level.txt
pywreck-0.6.0.dist-info/RECORD
