Metadata-Version: 2.4
Name: pywreck
Version: 0.6.0
Summary: Simple async HTTP/1.1 client
Home-page: https://a-feld.github.io/pywreck
Author: Allan Feldman
License: Apache-2.0
Project-URL: Source, https://github.com/a-feld/pywreck
Project-URL: Changelog, https://github.com/a-feld/pywreck/releases
Platform: any
Classifier: Development Status :: 3 - Alpha
Classifier: Topic :: Internet :: WWW/HTTP
Classifier: Programming Language :: Python :: Implementation :: CPython
Classifier: Programming Language :: Python :: 3 :: Only
Classifier: Programming Language :: Python :: 3.10
Classifier: Programming Language :: Python :: 3.11
Classifier: Programming Language :: Python :: 3.12
Classifier: Programming Language :: Python :: 3.13
Classifier: Programming Language :: Python :: 3.14
Classifier: Operating System :: OS Independent
Classifier: License :: OSI Approved :: Apache Software License
Requires-Python: >=3.10
License-File: LICENSE
Dynamic: license-file
